[
  {
    "time": "06:34 PM",
    "site": "login.live.com",
    "title": "Get a code to sign in",
    "url": "https://login.live.com/login.srf?wa=wsignin1%2E0&rpsnv=176&ct=1758114242&rver=7%2E5%2E2146%2E0&wp=MBI%5FSSL&wreply=https%3A%2F%2Fonedrive%2Elive%2Ecom%2F%5Fforms%2Fdefault%2Easpx%3Fapr%3D1&lc=2057&id=250206&wsucxt=1&cobrandid=11bd8083%2D87e0%2D41b5%2Dbb78%2D0bc43c8a8e8a&login%5Fhint=himanshuparate1528%40outlook%2Ecom&username=himanshuparate1528%40outlook%2Ecom&aadredir=1"
  },
  {
    "time": "06:33 PM",
    "site": "onedrive.live.com",
    "title": "Microsoft OneDrive",
    "url": "https://onedrive.live.com/login"
  },
  {
    "time": "06:33 PM",
    "site": "search.brave.com",
    "title": "onerdrive - Brave Search",
    "url": "https://search.brave.com/search?q=onerdrive&source=desktop"
  },
  {
    "time": "06:33 PM",
    "site": "newtab",
    "title": "New tab",
    "url": "chrome://newtab/"
  },
  {
    "time": "06:33 PM",
    "site": "discord.com",
    "title": "(39) Discord | #\u300e\ud83d\udcbb\u300f\ud835\ude41\ud835\ude50\ud835\ude49\ud835\ude3e\ud835\ude44\ud835\ude4a\ud835\ude49\ud835\ude40 | PANEL SAFE",
    "url": "https://discord.com/channels/1218333924053352519/1218346026705096764"
  }
]